gdm/__init__.py
gdm/constants.py
gdm/exceptions.py
gdm/hashing_utils.py
gdm/quantities.py
gdm/tracked_changes.py
gdm/version.py
gdm/cli/cli.py
gdm/cli/reducer.py
gdm/dataset/__init__.py
gdm/dataset/cost_model.py
gdm/dataset/dataset_system.py
gdm/distribution/__init__.py
gdm/distribution/catalog_system.py
gdm/distribution/distribution_graph.py
gdm/distribution/distribution_system.py
gdm/distribution/enums.py
gdm/distribution/sys_functools.py
gdm/distribution/common/__init__.py
gdm/distribution/common/curve.py
gdm/distribution/common/limitset.py
gdm/distribution/common/sequence_pair.py
gdm/distribution/components/__init__.py
gdm/distribution/components/distribution_battery.py
gdm/distribution/components/distribution_bus.py
gdm/distribution/components/distribution_capacitor.py
gdm/distribution/components/distribution_feeder.py
gdm/distribution/components/distribution_load.py
gdm/distribution/components/distribution_regulator.py
gdm/distribution/components/distribution_solar.py
gdm/distribution/components/distribution_substation.py
gdm/distribution/components/distribution_transformer.py
gdm/distribution/components/distribution_vsource.py
gdm/distribution/components/geometry_branch.py
gdm/distribution/components/matrix_impedance_branch.py
gdm/distribution/components/matrix_impedance_fuse.py
gdm/distribution/components/matrix_impedance_recloser.py
gdm/distribution/components/matrix_impedance_switch.py
gdm/distribution/components/sequence_impedance_branch.py
gdm/distribution/components/base/__init__.py
gdm/distribution/components/base/distribution_branch_base.py
gdm/distribution/components/base/distribution_component_base.py
gdm/distribution/components/base/distribution_switch_base.py
gdm/distribution/components/base/distribution_transformer_base.py
gdm/distribution/controllers/__init__.py
gdm/distribution/controllers/distribution_capacitor_controller.py
gdm/distribution/controllers/distribution_inverter_controller.py
grid_data_models-2.2.1.dist-info/METADATA
grid_data_models-2.2.1.dist-info/WHEEL
grid_data_models-2.2.1.dist-info/entry_points.txt
grid_data_models-2.2.1.dist-info/licenses/LICENSE.txt
grid_data_models-2.2.1.dist-info/RECORD
