Metadata-Version: 2.4
Name: grid-data-models
Version: 2.2.1
Project-URL: Documentation, https://github.com/NREL-Distribution-Suites/grid-data-models#readme
Project-URL: Issues, https://github.com/NREL-Distribution-Suites/grid-data-models/issues
Project-URL: Source, https://github.com/NREL-Distribution-Suites/grid-data-models
Author-email: Kapil Duwadi <Kapil.Duwadi@nrel.gov>, Aadil Latif <Aadil.Latif@nrel.gov>, Tarek Elgindy <tarek.elgindy@nrel.gov>
License-Expression: BSD-3-Clause
License-File: LICENSE.txt
Classifier: License :: OSI Approved :: BSD License
Classifier: Operating System :: OS Independent
Classifier: Programming Language :: Python :: 3.11
Requires-Python: >=3.11
Requires-Dist: click~=8.1.7
Requires-Dist: geopandas
Requires-Dist: importlib-metadata
Requires-Dist: infrasys~=1.0
Requires-Dist: networkx
Requires-Dist: pandas~=2.2.3
Requires-Dist: plotly
Requires-Dist: pydantic
Requires-Dist: semver
Provides-Extra: dev
Requires-Dist: docutils; extra == 'dev'
Requires-Dist: pre-commit; extra == 'dev'
Requires-Dist: pytest; extra == 'dev'
Requires-Dist: pytest-cov; extra == 'dev'
Requires-Dist: pytest-doctestplus; extra == 'dev'
Requires-Dist: ruff; extra == 'dev'
Provides-Extra: doc
Requires-Dist: autodoc-pydantic[erdantic]; extra == 'doc'
Requires-Dist: myst-parser; extra == 'doc'
Requires-Dist: pydata-sphinx-theme; extra == 'doc'
Requires-Dist: sphinx; extra == 'doc'
Requires-Dist: sphinxcontrib-mermaid; extra == 'doc'
